drupy/__init__.py
drupy/objects.py
drupy/resolver.py
drupy/runner.py
drupy/targets.py
drupy/utils.py
drupy-0.8.4.dist-info/LICENSE
drupy-0.8.4.dist-info/METADATA
drupy-0.8.4.dist-info/WHEEL
drupy-0.8.4.dist-info/entry_points.txt
drupy-0.8.4.dist-info/top_level.txt
drupy-0.8.4.dist-info/RECORD
