Metadata-Version: 2.1
Name: drupy
Version: 0.8.4
Summary: Python based deployment tool for Drupal 7
Author-email: Roman Zimmermann <torotil@gmail.com>
Project-URL: Homepage, https://github.com/moreonion/drupy
Keywords: drupal,drupy,build
Classifier: Development Status :: 3 - Alpha
Classifier: Environment :: Console
Classifier: Intended Audience :: Developers
Classifier: Intended Audience :: System Administrators
Classifier: License :: OSI Approved :: GNU General Public License v3 (GPLv3)
Classifier: Topic :: System :: Software Distribution
License-File: LICENSE
Provides-Extra: dev
Requires-Dist: black; extra == "dev"
Requires-Dist: isort; extra == "dev"
Requires-Dist: pre-commit; extra == "dev"
Requires-Dist: pydocstyle[toml]>=6; extra == "dev"
Requires-Dist: pylint; extra == "dev"
Requires-Dist: pytest; extra == "dev"
Requires-Dist: pytest-cov; extra == "dev"
Provides-Extra: yaml
Requires-Dist: ruamel.yaml>=0.16; extra == "yaml"
